nonebot_plugin_exhibitionism/__init__.py
nonebot_plugin_exhibitionism/draw.py
nonebot_plugin_exhibitionism/font.ttf
nonebot_plugin_exhibitionism-0.1.1.dist-info/METADATA
nonebot_plugin_exhibitionism-0.1.1.dist-info/WHEEL
nonebot_plugin_exhibitionism-0.1.1.dist-info/top_level.txt
nonebot_plugin_exhibitionism-0.1.1.dist-info/RECORD
